src/__init__.py
src/operations.py
wizza_calculator_lib-0.1.0.dist-info/METADATA
wizza_calculator_lib-0.1.0.dist-info/WHEEL
wizza_calculator_lib-0.1.0.dist-info/top_level.txt
wizza_calculator_lib-0.1.0.dist-info/RECORD
